dpspecs/__init__.py
dpspecs/settings.py
dpspecs-0.1.0.dist-info/METADATA
dpspecs-0.1.0.dist-info/WHEEL
dpspecs-0.1.0.dist-info/entry_points.txt
dpspecs-0.1.0.dist-info/licenses/LICENSE.md
dpspecs-0.1.0.dist-info/RECORD
