Metadata-Version: 2.1
Name: dpspecs
Version: 0.1.0
Summary: Python implementation of the Data Package standard
Project-URL: homepage, https://github.com/frictionlessdata/dpspecs-py
Author-email: Open Knowledge Foundation <info@okfn.org>
License-Expression: MIT
License-File: LICENSE.md
Keywords: data package,data validation,json schema,json table schema,open data,tabular data package
Classifier: Development Status :: 4 - Beta
Classifier: Environment :: Console
Classifier: Intended Audience :: Developers
Classifier: License :: OSI Approved :: MIT License
Classifier: Operating System :: OS Independent
Classifier: Programming Language :: Python :: 3
Classifier: Programming Language :: Python :: 3.8
Classifier: Programming Language :: Python :: 3.9
Classifier: Programming Language :: Python :: 3.10
Classifier: Programming Language :: Python :: 3.11
Classifier: Topic :: Software Development :: Libraries :: Python Modules
Requires-Python: >=3.8
Requires-Dist: pydantic>=2.0
Provides-Extra: dev
Requires-Dist: black; extra == 'dev'
Requires-Dist: hatch; extra == 'dev'
Requires-Dist: httpx; extra == 'dev'
Requires-Dist: ipython; extra == 'dev'
Requires-Dist: isort; extra == 'dev'
Requires-Dist: mkdocs; extra == 'dev'
Requires-Dist: mkdocs-material; extra == 'dev'
Requires-Dist: moto; extra == 'dev'
Requires-Dist: neovim; extra == 'dev'
Requires-Dist: oauth2client; extra == 'dev'
Requires-Dist: pyright; extra == 'dev'
Requires-Dist: pytest; extra == 'dev'
Requires-Dist: pytest-cov; extra == 'dev'
Requires-Dist: pytest-dotenv; extra == 'dev'
Requires-Dist: pytest-lazy-fixture; extra == 'dev'
Requires-Dist: pytest-mock; extra == 'dev'
Requires-Dist: pytest-only; extra == 'dev'
Requires-Dist: pytest-timeout; extra == 'dev'
Requires-Dist: pytest-vcr; extra == 'dev'
Requires-Dist: requests-mock; extra == 'dev'
Requires-Dist: ruff; extra == 'dev'
Requires-Dist: yattag; extra == 'dev'
